cvkit_neuro/__init__.py
cvkit_neuro/pose_estimation/post_processors/generative/heading_analysis.py
cvkit_neuro-0.0.1.dist-info/LICENSE
cvkit_neuro-0.0.1.dist-info/METADATA
cvkit_neuro-0.0.1.dist-info/WHEEL
cvkit_neuro-0.0.1.dist-info/top_level.txt
cvkit_neuro-0.0.1.dist-info/RECORD
