Metadata-Version: 2.1
Name: cvkit-neuro
Version: 0.0.1
Summary: A neuroscience related plugin for CVKit
Author-email: Mahir Patel <mahirp@bu.edu>
Project-URL: repository, https://github.com/mahir1010/cvkit-neuro
Classifier: Programming Language :: Python :: 3
Classifier: License :: OSI Approved :: MIT License
Classifier: Operating System :: OS Independent
Requires-Python: >=3.10
License-File: LICENSE
Requires-Dist: bu-cvkit
Requires-Dist: numpy (==1.24.2)
